odoo8_addon_website_blog_excerpt_img-8.0.1.0.0.99.dev12-py2.7-nspkg.pth
odoo8_addon_website_blog_excerpt_img-8.0.1.0.0.99.dev12.dist-info/DESCRIPTION.rst
odoo8_addon_website_blog_excerpt_img-8.0.1.0.0.99.dev12.dist-info/METADATA
odoo8_addon_website_blog_excerpt_img-8.0.1.0.0.99.dev12.dist-info/RECORD
odoo8_addon_website_blog_excerpt_img-8.0.1.0.0.99.dev12.dist-info/WHEEL
odoo8_addon_website_blog_excerpt_img-8.0.1.0.0.99.dev12.dist-info/metadata.json
odoo8_addon_website_blog_excerpt_img-8.0.1.0.0.99.dev12.dist-info/namespace_packages.txt
odoo8_addon_website_blog_excerpt_img-8.0.1.0.0.99.dev12.dist-info/top_level.txt
odoo_addons/website_blog_excerpt_img/README.rst
odoo_addons/website_blog_excerpt_img/__init__.py
odoo_addons/website_blog_excerpt_img/__openerp__.py
odoo_addons/website_blog_excerpt_img/i18n/es.po
odoo_addons/website_blog_excerpt_img/i18n/eu.po
odoo_addons/website_blog_excerpt_img/i18n/fr.po
odoo_addons/website_blog_excerpt_img/i18n/pt_BR.po
odoo_addons/website_blog_excerpt_img/i18n/sl.po
odoo_addons/website_blog_excerpt_img/i18n/website_blog_excerpt_img.pot
odoo_addons/website_blog_excerpt_img/images/style-default.png
odoo_addons/website_blog_excerpt_img/static/description/icon.png
odoo_addons/website_blog_excerpt_img/static/src/css/website_blog_excerpt_img.css
odoo_addons/website_blog_excerpt_img/static/src/css/website_blog_excerpt_img.css.map
odoo_addons/website_blog_excerpt_img/static/src/css/website_blog_excerpt_img.sass
odoo_addons/website_blog_excerpt_img/views/assets.xml
odoo_addons/website_blog_excerpt_img/views/blog.xml
